{
  "type": "FeatureCollection",
  "features": [
    {
      "type": "Feature",
      "geometry": {
        "type": "LineString",
        "coordinates": [
          [
            -1.626118711,
            47.210815432
          ],
          [
            -1.62816534,
            47.210870602
          ],
          [
            -1.629000234,
            47.21107142
          ],
          [
            -1.630130752,
            47.211294304
          ],
          [
            -1.631135531,
            47.211631939
          ],
          [
            -1.637690357,
            47.214636328
          ],
          [
            -1.638061504,
            47.214822088
          ],
          [
            -1.63813964,
            47.215021115
          ],
          [
            -1.638315446,
            47.215113994
          ],
          [
            -1.63854497,
            47.215137214
          ],
          [
            -1.638696359,
            47.21508414
          ],
          [
            -1.641821676,
            47.216491401
          ],
          [
            -1.643526019,
            47.217267578
          ],
          [
            -1.643932522,
            47.217342162
          ]
        ]
      },
      "properties": {
        "line": "C",
        "name": "D17/Boulevard Charles de Gaulle",
        "status": "unknown",
        "doneAt": "01/01/2000",
        "type": "bidirectionnelle",
        "quality": "not-rated-yet",
        "infrastructure": "magistrale",
        "link": ""
      }
    },
    {
      "type": "Feature",
      "geometry": {
        "type": "LineString",
        "coordinates": [
          [
            -1.552179203,
            47.21326126
          ],
          [
            -1.550141738,
            47.214061352
          ],
          [
            -1.548462037,
            47.214837375
          ],
          [
            -1.547206361,
            47.215457294
          ],
          [
            -1.547209424,
            47.215500984
          ],
          [
            -1.546689287,
            47.215687627
          ],
          [
            -1.546339753,
            47.215839911
          ],
          [
            -1.546110795,
            47.215980345
          ],
          [
            -1.545950754,
            47.216106214
          ],
          [
            -1.545750129,
            47.216183192
          ],
          [
            -1.545561755,
            47.216243526
          ],
          [
            -1.545468334,
            47.216337148
          ],
          [
            -1.545452253,
            47.216411004
          ],
          [
            -1.545472929,
            47.216482781
          ],
          [
            -1.545472929,
            47.216572241
          ],
          [
            -1.545297186,
            47.216738735
          ],
          [
            -1.545082777,
            47.216890608
          ],
          [
            -1.544761806,
            47.217032173
          ],
          [
            -1.544293636,
            47.217197251
          ],
          [
            -1.544032491,
            47.217285033
          ],
          [
            -1.543834929,
            47.217329762
          ]
        ]
      },
      "properties": {
        "line": "C",
        "name": "Cours Commandant d'Estienne d'Orves/Kennedy",
        "status": "unknown",
        "doneAt": "01/01/2000",
        "type": "bidirectionnelle",
        "quality": "not-rated-yet",
        "infrastructure": "magistrale",
        "link": ""
      }
    },
    {
      "type": "Feature",
      "geometry": {
        "type": "LineString",
        "coordinates": [
          [
            -1.549054,
            47.191492
          ],
          [
            -1.54811,
            47.191631
          ],
          [
            -1.543976,
            47.177055
          ],
          [
            -1.541585,
            47.157297
          ],
          [
            -1.538416,
            47.156626
          ],
          [
            -1.533137,
            47.149914
          ],
          [
            -1.531379,
            47.148438
          ],
          [
            -1.519148,
            47.133916
          ],
          [
            -1.517384,
            47.132905
          ]
        ]
      },
      "properties": {
        "line": "C",
        "name": "Rezé - Les Sorinières",
        "status": "postponed",
        "doneAt": "01/01/2000",
        "type": "inconnu",
        "quality": "not-rated-yet",
        "infrastructure": "magistrale",
        "link": ""
      }
    },
    {
      "type": "Feature",
      "geometry": {
        "type": "LineString",
        "coordinates": [
          [
            -1.56219437,
            47.196333557
          ],
          [
            -1.562314073,
            47.196416848
          ],
          [
            -1.56216144,
            47.196876174
          ],
          [
            -1.561642073,
            47.199676719
          ],
          [
            -1.561721564,
            47.19968104
          ],
          [
            -1.561708846,
            47.199758814
          ],
          [
            -1.561912343,
            47.199765295
          ]
        ]
      },
      "properties": {
        "line": "C",
        "name": "Pont des 3 continents",
        "status": "unknown",
        "doneAt": "01/01/2000",
        "type": "bidirectionnelle",
        "quality": "not-rated-yet",
        "infrastructure": "magistrale",
        "link": ""
      }
    },
    {
      "type": "Feature",
      "geometry": {
        "type": "LineString",
        "coordinates": [
          [
            -1.561908189,
            47.199766339
          ],
          [
            -1.56194898,
            47.199834968
          ],
          [
            -1.561939268,
            47.199941869
          ],
          [
            -1.561822722,
            47.200170189
          ],
          [
            -1.561802991,
            47.201320934
          ],
          [
            -1.56181853,
            47.201536051
          ],
          [
            -1.561861264,
            47.2015928
          ],
          [
            -1.561931191,
            47.201620514
          ],
          [
            -1.561973925,
            47.201631072
          ]
        ]
      },
      "properties": {
        "line": "C",
        "name": "Boulevard Simone Veil",
        "status": "done",
        "doneAt": "01/01/2000",
        "type": "bidirectionnelle",
        "quality": "not-rated-yet",
        "infrastructure": "magistrale",
        "link": "",
        "id": "sans-titre#87"
      }
    },
    {
      "type": "Feature",
      "geometry": {
        "type": "LineString",
        "coordinates": [
          [
            -1.561973355,
            47.201630167
          ],
          [
            -1.562096384,
            47.201644614
          ],
          [
            -1.562574827,
            47.20164255
          ],
          [
            -1.562675072,
            47.201648742
          ],
          [
            -1.562928723,
            47.20171685
          ],
          [
            -1.563062383,
            47.201765353
          ],
          [
            -1.563130732,
            47.201834493
          ],
          [
            -1.563241115,
            47.202006909
          ],
          [
            -1.563915004,
            47.203509317
          ],
          [
            -1.563882037,
            47.203593738
          ]
        ]
      },
      "properties": {
        "line": "C",
        "name": "Rue Simone Veil",
        "status": "done",
        "doneAt": "01/01/2000",
        "type": "bidirectionnelle",
        "quality": "not-rated-yet",
        "infrastructure": "magistrale",
        "link": "",
        "id": "sans-titre#89"
      }
    },
    {
      "type": "Feature",
      "geometry": {
        "type": "LineString",
        "coordinates": [
          [
            -1.563896818,
            47.203587454
          ],
          [
            -1.562449993,
            47.204514374
          ],
          [
            -1.566525681,
            47.208957047
          ]
        ]
      },
      "properties": {
        "line": "C",
        "name": "Pont Anne de Bretagne/Bd Léon Bureau",
        "status": "postponed",
        "doneAt": "01/01/2000",
        "type": "inconnu",
        "quality": "not-rated-yet",
        "infrastructure": "magistrale",
        "link": ""
      }
    },
    {
      "type": "Feature",
      "geometry": {
        "type": "LineString",
        "coordinates": [
          [
            -1.552176295,
            47.213262376
          ],
          [
            -1.552427307,
            47.213281572
          ],
          [
            -1.553647455,
            47.212761022
          ],
          [
            -1.554144364,
            47.212555781
          ],
          [
            -1.554475168,
            47.212220411
          ],
          [
            -1.555762041,
            47.211890434
          ],
          [
            -1.556674475,
            47.211572154
          ]
        ]
      },
      "properties": {
        "line": "C",
        "name": "Boulevard Jean Philippot",
        "status": "unknown",
        "doneAt": "01/01/2000",
        "type": "bandes-cyclables",
        "quality": "not-rated-yet",
        "infrastructure": "magistrale",
        "link": ""
      }
    },
    {
      "type": "Feature",
      "geometry": {
        "type": "LineString",
        "coordinates": [
          [
            -1.556672202,
            47.211574692
          ],
          [
            -1.557366936,
            47.211191531
          ],
          [
            -1.558181267,
            47.210963887
          ],
          [
            -1.560911382,
            47.209858627
          ],
          [
            -1.561181021,
            47.209885688
          ],
          [
            -1.561312568,
            47.209786295
          ]
        ]
      },
      "properties": {
        "line": "C",
        "name": "Gloriette",
        "status": "postponed",
        "doneAt": "01/01/2000",
        "type": "bidirectionnelle",
        "quality": "not-rated-yet",
        "infrastructure": "magistrale",
        "link": ""
      }
    },
    {
      "type": "Feature",
      "geometry": {
        "type": "LineString",
        "coordinates": [
          [
            -1.556351255,
            47.209378448
          ],
          [
            -1.557595951,
            47.209506625
          ],
          [
            -1.558224785,
            47.209542957
          ],
          [
            -1.558500036,
            47.209541474
          ],
          [
            -1.558599683,
            47.209360914
          ],
          [
            -1.559079412,
            47.209452295
          ],
          [
            -1.560069663,
            47.20954698
          ],
          [
            -1.56076225,
            47.20962316
          ],
          [
            -1.561687673,
            47.209863172
          ],
          [
            -1.562425458,
            47.210038309
          ],
          [
            -1.562848462,
            47.210058127
          ],
          [
            -1.563271466,
            47.2100273
          ],
          [
            -1.563652332,
            47.209950232
          ],
          [
            -1.566231482,
            47.209156542
          ],
          [
            -1.566360776,
            47.209084927
          ],
          [
            -1.566402454,
            47.208979125
          ],
          [
            -1.56661304,
            47.208910577
          ],
          [
            -1.569970051,
            47.207849729
          ],
          [
            -1.571552456,
            47.207106917
          ],
          [
            -1.572251466,
            47.207247809
          ]
        ]
      },
      "properties": {
        "line": "C",
        "name": "Quai de la fosse",
        "status": "unknown",
        "doneAt": "01/01/2000",
        "type": "bidirectionnelle",
        "quality": "not-rated-yet",
        "infrastructure": "magistrale",
        "link": "",
        "id": "sans-titre#105"
      }
    },
    {
      "type": "Feature",
      "geometry": {
        "type": "LineString",
        "coordinates": [
          [
            -1.572248648,
            47.20724882
          ],
          [
            -1.572626628,
            47.207152349
          ],
          [
            -1.573894223,
            47.206926778
          ],
          [
            -1.575875061,
            47.206570592
          ],
          [
            -1.576307338,
            47.206520937
          ],
          [
            -1.576919208,
            47.2065181
          ],
          [
            -1.577879902,
            47.206683823
          ],
          [
            -1.579126785,
            47.206963344
          ],
          [
            -1.585985085,
            47.208476174
          ],
          [
            -1.586744044,
            47.208671611
          ],
          [
            -1.587269947,
            47.208850241
          ],
          [
            -1.588599117,
            47.209345459
          ],
          [
            -1.589022635,
            47.209491709
          ],
          [
            -1.589841435,
            47.209717076
          ],
          [
            -1.590544879,
            47.20985167
          ],
          [
            -1.59144838,
            47.209952365
          ],
          [
            -1.59252482,
            47.209949968
          ],
          [
            -1.596285329,
            47.209559174
          ],
          [
            -1.597908608,
            47.209624368
          ],
          [
            -1.599263892,
            47.209684412
          ]
        ]
      },
      "properties": {
        "line": "C",
        "name": "Boulevard René Coty",
        "status": "unknown",
        "doneAt": "01/01/2000",
        "type": "bandes-cyclables",
        "quality": "not-rated-yet",
        "infrastructure": "magistrale",
        "link": ""
      }
    },
    {
      "type": "Feature",
      "geometry": {
        "type": "LineString",
        "coordinates": [
          [
            -1.599261577,
            47.209684036
          ],
          [
            -1.600227185,
            47.209744772
          ],
          [
            -1.602237794,
            47.209967328
          ],
          [
            -1.60339077,
            47.210097556
          ],
          [
            -1.60596788,
            47.210365794
          ],
          [
            -1.60762286,
            47.210605724
          ],
          [
            -1.609509937,
            47.211051304
          ]
        ]
      },
      "properties": {
        "line": "C",
        "name": "Boulevard Emile Romanet",
        "status": "wip",
        "doneAt": "01/01/2000",
        "type": "bandes-cyclables",
        "quality": "not-rated-yet",
        "infrastructure": "magistrale",
        "link": ""
      }
    },
    {
      "type": "Feature",
      "geometry": {
        "type": "LineString",
        "coordinates": [
          [
            -1.609511877,
            47.211051607
          ],
          [
            -1.609990378,
            47.211215133
          ],
          [
            -1.610269501,
            47.211276329
          ],
          [
            -1.612924537,
            47.211426238
          ],
          [
            -1.614922425,
            47.211559687
          ],
          [
            -1.616178208,
            47.211541995
          ],
          [
            -1.617612686,
            47.21127006
          ],
          [
            -1.618821974,
            47.210967597
          ],
          [
            -1.619919145,
            47.210700695
          ],
          [
            -1.620939986,
            47.210654781
          ]
        ]
      },
      "properties": {
        "line": "C",
        "name": "Rue de Saint nazaire",
        "status": "unknown",
        "doneAt": "01/01/2000",
        "type": "bandes-cyclables",
        "quality": "not-rated-yet",
        "infrastructure": "magistrale",
        "link": ""
      }
    },
    {
      "type": "Feature",
      "geometry": {
        "type": "LineString",
        "coordinates": [
          [
            -1.620938452,
            47.21065507
          ],
          [
            -1.626125268,
            47.210814496
          ]
        ]
      },
      "properties": {
        "line": "C",
        "name": "Boulevard Charles de Gaulle",
        "status": "done",
        "doneAt": "01/01/2000",
        "type": "bandes-cyclables",
        "quality": "not-rated-yet",
        "infrastructure": "magistrale",
        "link": ""
      }
    },
    {
      "type": "Feature",
      "geometry": {
        "type": "LineString",
        "coordinates": [
          [
            -1.546143,
            47.194438
          ],
          [
            -1.546593,
            47.194851
          ],
          [
            -1.549093,
            47.195537
          ],
          [
            -1.549865,
            47.195515
          ]
        ]
      },
      "properties": {
        "line": "C",
        "name": "C#160",
        "status": "unknown",
        "doneAt": "01/01/2000",
        "type": "inconnu",
        "quality": "not-rated-yet",
        "infrastructure": "structurante",
        "link": "",
        "id": "sans-titre#160"
      }
    },
    {
      "type": "Feature",
      "geometry": {
        "type": "LineString",
        "coordinates": [
          [
            -1.549865,
            47.195515
          ],
          [
            -1.550184,
            47.195634
          ],
          [
            -1.552931,
            47.195779
          ],
          [
            -1.555999,
            47.196159
          ],
          [
            -1.557909,
            47.196581
          ],
          [
            -1.5622,
            47.196304
          ]
        ]
      },
      "properties": {
        "line": "C",
        "name": "C#162",
        "status": "unknown",
        "doneAt": "01/01/2000",
        "type": "inconnu",
        "quality": "not-rated-yet",
        "infrastructure": "maillage",
        "link": "",
        "id": "sans-titre#162"
      }
    },
    {
      "type": "Feature",
      "geometry": {
        "type": "LineString",
        "coordinates": [
          [
            -1.549766151,
            47.195604833
          ],
          [
            -1.549533,
            47.193534
          ],
          [
            -1.549054,
            47.191492
          ]
        ]
      },
      "properties": {
        "line": "C",
        "name": "Rezé - Les Sorinières",
        "status": "postponed",
        "doneAt": "01/01/2000",
        "type": "inconnu",
        "quality": "not-rated-yet",
        "infrastructure": "magistrale",
        "link": "",
        "id": "sans-titre#170"
      }
    }
  ]
}